psychsem/__init__.py
psychsem/main.py
psychsem-1.6.2.dist-info/METADATA
psychsem-1.6.2.dist-info/WHEEL
psychsem-1.6.2.dist-info/top_level.txt
psychsem-1.6.2.dist-info/RECORD
