Metadata-Version: 2.4
Name: psychsem
Version: 1.6.2
Summary: Y12
Author: Psych
Dynamic: author
Dynamic: summary
